spectro/__init__.py
spectro/_main.py
spectro/cli.py
spectro-0.2.0.dist-info/LICENSE
spectro-0.2.0.dist-info/METADATA
spectro-0.2.0.dist-info/WHEEL
spectro-0.2.0.dist-info/entry_points.txt
spectro-0.2.0.dist-info/top_level.txt
spectro-0.2.0.dist-info/RECORD
