Metadata-Version: 2.1
Name: spectro
Version: 0.2.0
Summary: Audio file spectral analysis
Home-page: https://github.com/nschloe/spectro
Author: Nico Schlömer
Author-email: nico.schloemer@gmail.com
License: GPL-3.0-or-later
Project-URL: Code, https://github.com/nschloe/spectro
Project-URL: Issues, https://github.com/nschloe/spectro/issues
Project-URL: Funding, https://github.com/sponsors/nschloe
Platform: UNKNOWN
Classifier: Development Status :: 4 - Beta
Classifier: Intended Audience :: Science/Research
Classifier: License :: OSI Approved :: MIT License
Classifier: Operating System :: OS Independent
Classifier: Programming Language :: Python :: 3
Classifier: Programming Language :: Python :: 3.8
Classifier: Programming Language :: Python :: 3.9
Classifier: Programming Language :: Python :: 3.10
Classifier: Topic :: Scientific/Engineering
Classifier: Topic :: Utilities
Requires-Python: >=3.8
License-File: LICENSE
Requires-Dist: matplotlib
Requires-Dist: mutagen
Requires-Dist: numpy
Requires-Dist: pydub
Requires-Dist: rich
Requires-Dist: scipy
